e2eAIOK/__init__.py
e2eAIOK/version
e2eAIOK/DeNas/__init__.py
e2eAIOK/DeNas/search.py
e2eAIOK/DeNas/train.py
e2eAIOK/DeNas/utils.py
e2eAIOK/DeNas/asr/TransformerBase.py
e2eAIOK/DeNas/asr/TransformerLM.py
e2eAIOK/DeNas/asr/__init__.py
e2eAIOK/DeNas/asr/asr_model_builder.py
e2eAIOK/DeNas/asr/asr_trainer.py
e2eAIOK/DeNas/asr/init_asr_parser.py
e2eAIOK/DeNas/asr/model_builder_denas_asr.py
e2eAIOK/DeNas/asr/supernet_asr.py
e2eAIOK/DeNas/asr/data/__init__.py
e2eAIOK/DeNas/asr/data/augment.py
e2eAIOK/DeNas/asr/data/features.py
e2eAIOK/DeNas/asr/data/librispeech_prepare.py
e2eAIOK/DeNas/asr/data/dataio/__init__.py
e2eAIOK/DeNas/asr/data/dataio/batch.py
e2eAIOK/DeNas/asr/data/dataio/dataio.py
e2eAIOK/DeNas/asr/data/dataio/dataloader.py
e2eAIOK/DeNas/asr/data/dataio/dataset.py
e2eAIOK/DeNas/asr/data/dataio/sampler.py
e2eAIOK/DeNas/asr/data/dataio/wer.py
e2eAIOK/DeNas/asr/data/processing/__init__.py
e2eAIOK/DeNas/asr/data/processing/features.py
e2eAIOK/DeNas/asr/data/processing/signal_processing.py
e2eAIOK/DeNas/asr/data/processing/speech_augmentation.py
e2eAIOK/DeNas/asr/decoders/__init__.py
e2eAIOK/DeNas/asr/decoders/ctc.py
e2eAIOK/DeNas/asr/decoders/seq2seq.py
e2eAIOK/DeNas/asr/lib/CNN.py
e2eAIOK/DeNas/asr/lib/__init__.py
e2eAIOK/DeNas/asr/lib/containers.py
e2eAIOK/DeNas/asr/lib/convolution.py
e2eAIOK/DeNas/asr/trainer/__init__.py
e2eAIOK/DeNas/asr/trainer/losses.py
e2eAIOK/DeNas/asr/trainer/schedulers.py
e2eAIOK/DeNas/asr/utils/Accuracy.py
e2eAIOK/DeNas/asr/utils/__init__.py
e2eAIOK/DeNas/asr/utils/asr_nas.py
e2eAIOK/DeNas/asr/utils/checkpoints.py
e2eAIOK/DeNas/asr/utils/data_pipeline.py
e2eAIOK/DeNas/asr/utils/data_utils.py
e2eAIOK/DeNas/asr/utils/depgraph.py
e2eAIOK/DeNas/asr/utils/distributed.py
e2eAIOK/DeNas/asr/utils/edit_distance.py
e2eAIOK/DeNas/asr/utils/metric_stats.py
e2eAIOK/DeNas/asr/utils/parameter_transfer.py
e2eAIOK/DeNas/asr/utils/utils.py
e2eAIOK/DeNas/cv/DeNet.py
e2eAIOK/DeNas/cv/__init__.py
e2eAIOK/DeNas/cv/benchmark_network_latency.py
e2eAIOK_denas-1.1.0.dist-info/LICENSE
e2eAIOK_denas-1.1.0.dist-info/METADATA
e2eAIOK_denas-1.1.0.dist-info/WHEEL
e2eAIOK_denas-1.1.0.dist-info/top_level.txt
e2eAIOK_denas-1.1.0.dist-info/RECORD
