Metadata-Version: 2.1
Name: e2eAIOK-denas
Version: 1.1.0
Summary: Intel® End-to-End AI Optimization Kit
Home-page: https://github.com/intel/e2eAIOK
Author: INTEL
License: Apache License
Project-URL: Bug Tracker, https://github.com/intel/e2eAIOK/issues
Platform: UNKNOWN
Classifier: Programming Language :: Python :: 3
Classifier: License :: OSI Approved :: Apache Software License
Classifier: Operating System :: OS Independent
Requires-Python: >=3.6
Requires-Dist: easydict
Requires-Dist: sentencepiece
Requires-Dist: opencv-python
Requires-Dist: scikit-image
Requires-Dist: timm
Requires-Dist: boto3
Requires-Dist: ptflops
Requires-Dist: sigopt
Requires-Dist: tensorboard
Requires-Dist: thop
Requires-Dist: transformers
Requires-Dist: torchaudio (~=0.12.0)
